{
    "MSE": 0.004182042819922409,
    "RMSE": 0.0646687159291292,
    "MAE": 0.04996704582422479,
    "R2": 0.9385369981720947,
    "train_rmse": 0.0891530468603876,
    "train_mae": 0.06289417045178078,
    "test_rmse": 0.0646687159291292,
    "test_mae": 0.04996704582422479,
    "test_predictions": [
        [
            -1.203597903251648
        ],
        [
            -1.2541626691818237
        ],
        [
            -1.3066011667251587
        ],
        [
            -1.3041021823883057
        ],
        [
            -1.3491482734680176
        ],
        [
            -1.3587281703948975
        ],
        [
            -1.4276751279830933
        ],
        [
            -1.433833122253418
        ],
        [
            -1.3092544078826904
        ],
        [
            -1.3090864419937134
        ],
        [
            -1.2674753665924072
        ],
        [
            -1.1468305587768555
        ],
        [
            -1.1396045684814453
        ],
        [
            -1.130327582359314
        ],
        [
            -1.1388640403747559
        ],
        [
            -1.163512110710144
        ],
        [
            -1.1937448978424072
        ],
        [
            -1.2102665901184082
        ],
        [
            -1.2047271728515625
        ],
        [
            -1.2055515050888062
        ],
        [
            -1.2311149835586548
        ],
        [
            -1.23442542552948
        ],
        [
            -1.2160849571228027
        ],
        [
            -1.189530611038208
        ],
        [
            -1.1849316358566284
        ],
        [
            -1.1883366107940674
        ],
        [
            -1.207687497138977
        ],
        [
            -1.2486270666122437
        ],
        [
            -1.3199955224990845
        ],
        [
            -1.3413841724395752
        ],
        [
            -1.3516045808792114
        ],
        [
            -1.3332715034484863
        ],
        [
            -1.372375249862671
        ],
        [
            -1.3447126150131226
        ],
        [
            -1.4172812700271606
        ],
        [
            -1.4336107969284058
        ],
        [
            -1.4236035346984863
        ],
        [
            -1.5212305784225464
        ],
        [
            -1.5198115110397339
        ],
        [
            -1.4424450397491455
        ],
        [
            -1.4040509462356567
        ],
        [
            -1.3975985050201416
        ],
        [
            -1.4108020067214966
        ],
        [
            -1.5149034261703491
        ],
        [
            -1.5447869300842285
        ],
        [
            -1.521693229675293
        ],
        [
            -1.5065908432006836
        ],
        [
            -1.3423101902008057
        ],
        [
            -1.2281895875930786
        ],
        [
            -1.1771897077560425
        ],
        [
            -1.0487544536590576
        ],
        [
            -1.1691148281097412
        ],
        [
            -1.0842928886413574
        ],
        [
            -1.05326509475708
        ],
        [
            -1.0700385570526123
        ],
        [
            -1.0338490009307861
        ],
        [
            -1.0319714546203613
        ],
        [
            -0.9962350130081177
        ],
        [
            -0.967381477355957
        ],
        [
            -0.9933297634124756
        ],
        [
            -1.0168087482452393
        ],
        [
            -1.0264606475830078
        ],
        [
            -0.9097098112106323
        ],
        [
            -0.9739114046096802
        ],
        [
            -0.9642384052276611
        ],
        [
            -1.036292314529419
        ],
        [
            -1.1002367734909058
        ],
        [
            -1.0675442218780518
        ],
        [
            -1.0074257850646973
        ],
        [
            -0.917668879032135
        ],
        [
            -0.8748461008071899
        ],
        [
            -0.8508906364440918
        ],
        [
            -0.9443883895874023
        ],
        [
            -0.9508669376373291
        ],
        [
            -1.0571870803833008
        ],
        [
            -1.0646315813064575
        ],
        [
            -1.1132315397262573
        ],
        [
            -1.1329331398010254
        ],
        [
            -1.1508445739746094
        ],
        [
            -1.2154905796051025
        ],
        [
            -1.191115140914917
        ],
        [
            -1.1433230638504028
        ],
        [
            -1.1287157535552979
        ],
        [
            -1.0584235191345215
        ],
        [
            -1.077756404876709
        ],
        [
            -1.1505498886108398
        ],
        [
            -1.1322091817855835
        ],
        [
            -1.1016976833343506
        ],
        [
            -1.0670199394226074
        ],
        [
            -1.1034424304962158
        ],
        [
            -1.1297545433044434
        ],
        [
            -1.1023715734481812
        ],
        [
            -1.103466272354126
        ],
        [
            -1.1272785663604736
        ],
        [
            -1.0706331729888916
        ],
        [
            -1.0161291360855103
        ],
        [
            -0.9727640151977539
        ],
        [
            -0.9418528079986572
        ],
        [
            -0.889394998550415
        ],
        [
            -0.8132578134536743
        ],
        [
            -0.8317384719848633
        ],
        [
            -0.811196506023407
        ],
        [
            -0.8474115133285522
        ],
        [
            -0.8696777820587158
        ],
        [
            -0.8195943832397461
        ],
        [
            -0.7809221148490906
        ],
        [
            -0.6514183282852173
        ],
        [
            -0.6318308115005493
        ],
        [
            -0.552973747253418
        ],
        [
            -0.6262555122375488
        ],
        [
            -0.651540994644165
        ],
        [
            -0.6746195554733276
        ],
        [
            -0.7498443126678467
        ],
        [
            -0.8323441743850708
        ],
        [
            -0.908174991607666
        ],
        [
            -0.9376518726348877
        ],
        [
            -0.9636259078979492
        ],
        [
            -0.9789648056030273
        ],
        [
            -0.9342554211616516
        ],
        [
            -0.9143348932266235
        ],
        [
            -0.9297631978988647
        ],
        [
            -0.9809057712554932
        ],
        [
            -0.9379985332489014
        ],
        [
            -0.9098027348518372
        ],
        [
            -0.888410210609436
        ],
        [
            -0.911672830581665
        ],
        [
            -0.9106737375259399
        ],
        [
            -0.904528796672821
        ],
        [
            -0.9154913425445557
        ],
        [
            -0.9269881248474121
        ],
        [
            -0.9330111145973206
        ],
        [
            -0.9036628603935242
        ],
        [
            -0.9705958366394043
        ],
        [
            -0.9864064455032349
        ],
        [
            -0.9717292785644531
        ],
        [
            -0.959937334060669
        ],
        [
            -0.8596831560134888
        ],
        [
            -0.7954294681549072
        ],
        [
            -0.7877667546272278
        ],
        [
            -0.8493394255638123
        ],
        [
            -0.8584665656089783
        ],
        [
            -0.7634456753730774
        ],
        [
            -0.7634425163269043
        ],
        [
            -0.7767651081085205
        ],
        [
            -0.7900813817977905
        ],
        [
            -0.8210722804069519
        ],
        [
            -0.8463510274887085
        ],
        [
            -0.8279502987861633
        ],
        [
            -0.8855414390563965
        ],
        [
            -0.9004048705101013
        ],
        [
            -0.8856841921806335
        ],
        [
            -0.8992876410484314
        ],
        [
            -0.933029294013977
        ],
        [
            -0.9516546726226807
        ],
        [
            -0.9696269035339355
        ],
        [
            -0.9676547050476074
        ],
        [
            -0.874406099319458
        ],
        [
            -0.8583381175994873
        ],
        [
            -0.7294619679450989
        ],
        [
            -0.8134521245956421
        ],
        [
            -0.8625296354293823
        ],
        [
            -0.8834059238433838
        ],
        [
            -0.8453969955444336
        ],
        [
            -0.8048359155654907
        ],
        [
            -0.8386512398719788
        ],
        [
            -0.8562262058258057
        ],
        [
            -0.892446756362915
        ],
        [
            -0.909645676612854
        ],
        [
            -0.9106271862983704
        ],
        [
            -0.9346151351928711
        ],
        [
            -0.962996244430542
        ],
        [
            -0.9229042530059814
        ],
        [
            -0.9540238380432129
        ],
        [
            -0.9591987133026123
        ],
        [
            -0.9534590244293213
        ],
        [
            -1.0096105337142944
        ],
        [
            -1.0444331169128418
        ],
        [
            -1.0326186418533325
        ],
        [
            -1.1002414226531982
        ],
        [
            -1.1126314401626587
        ],
        [
            -1.1392889022827148
        ],
        [
            -1.2070872783660889
        ],
        [
            -1.238541841506958
        ],
        [
            -1.19871985912323
        ],
        [
            -1.2561988830566406
        ],
        [
            -1.4123550653457642
        ],
        [
            -1.4598324298858643
        ],
        [
            -1.4296557903289795
        ],
        [
            -1.4315266609191895
        ],
        [
            -1.3764604330062866
        ],
        [
            -1.3344823122024536
        ],
        [
            -1.2367424964904785
        ],
        [
            -1.2654321193695068
        ],
        [
            -1.280332326889038
        ],
        [
            -1.247434377670288
        ],
        [
            -1.2790218591690063
        ],
        [
            -1.3303947448730469
        ],
        [
            -1.385511040687561
        ],
        [
            -1.3348811864852905
        ],
        [
            -1.3293447494506836
        ],
        [
            -1.2699607610702515
        ],
        [
            -1.3115814924240112
        ],
        [
            -1.3669679164886475
        ],
        [
            -1.3630131483078003
        ],
        [
            -1.344614028930664
        ],
        [
            -1.3739711046218872
        ],
        [
            -1.2599841356277466
        ],
        [
            -1.273313045501709
        ],
        [
            -1.2995407581329346
        ],
        [
            -1.2464628219604492
        ],
        [
            -1.1850755214691162
        ],
        [
            -1.1647976636886597
        ],
        [
            -1.1787618398666382
        ],
        [
            -1.178682565689087
        ],
        [
            -1.1884582042694092
        ],
        [
            -1.1926116943359375
        ],
        [
            -1.1871979236602783
        ],
        [
            -1.1895439624786377
        ],
        [
            -1.1594146490097046
        ],
        [
            -1.1214523315429688
        ],
        [
            -1.1398289203643799
        ],
        [
            -1.1624231338500977
        ],
        [
            -1.15815007686615
        ],
        [
            -1.1980212926864624
        ],
        [
            -1.2269864082336426
        ],
        [
            -1.2060294151306152
        ],
        [
            -1.2172985076904297
        ],
        [
            -1.1850444078445435
        ],
        [
            -1.241936206817627
        ],
        [
            -1.2168290615081787
        ],
        [
            -1.1945817470550537
        ],
        [
            -1.1011439561843872
        ],
        [
            -1.062804937362671
        ],
        [
            -1.0980377197265625
        ],
        [
            -1.060230016708374
        ],
        [
            -1.0993568897247314
        ],
        [
            -1.1528819799423218
        ],
        [
            -1.209702491760254
        ],
        [
            -1.1592694520950317
        ],
        [
            -1.2088394165039062
        ],
        [
            -1.2402215003967285
        ],
        [
            -1.2220771312713623
        ],
        [
            -1.2632931470870972
        ],
        [
            -1.2580430507659912
        ],
        [
            -1.2579268217086792
        ],
        [
            -1.2561289072036743
        ],
        [
            -1.257718801498413
        ],
        [
            -1.2236955165863037
        ],
        [
            -1.2125194072723389
        ],
        [
            -1.1678861379623413
        ],
        [
            -1.1145247220993042
        ],
        [
            -1.0918563604354858
        ],
        [
            -1.1243064403533936
        ],
        [
            -1.1736135482788086
        ],
        [
            -1.1505544185638428
        ],
        [
            -1.1602342128753662
        ],
        [
            -1.214951992034912
        ],
        [
            -1.2275891304016113
        ],
        [
            -1.1877057552337646
        ],
        [
            -1.0900143384933472
        ],
        [
            -1.0910460948944092
        ],
        [
            -1.1353442668914795
        ],
        [
            -1.219302773475647
        ],
        [
            -1.2684072256088257
        ],
        [
            -1.2715990543365479
        ],
        [
            -1.234054446220398
        ],
        [
            -1.1891692876815796
        ],
        [
            -1.1845544576644897
        ],
        [
            -1.1865448951721191
        ],
        [
            -1.1702123880386353
        ],
        [
            -1.1819998025894165
        ],
        [
            -1.2469390630722046
        ],
        [
            -1.307654857635498
        ],
        [
            -1.3455681800842285
        ],
        [
            -1.336044430732727
        ],
        [
            -1.3198703527450562
        ],
        [
            -1.390674352645874
        ],
        [
            -1.4115272760391235
        ],
        [
            -1.4558268785476685
        ],
        [
            -1.6060264110565186
        ],
        [
            -1.6968412399291992
        ],
        [
            -1.7952120304107666
        ],
        [
            -1.7582682371139526
        ],
        [
            -1.8328347206115723
        ],
        [
            -1.8236483335494995
        ],
        [
            -1.7891345024108887
        ],
        [
            -1.7474462985992432
        ],
        [
            -1.7728272676467896
        ],
        [
            -1.7623634338378906
        ],
        [
            -1.7836248874664307
        ],
        [
            -1.7328925132751465
        ],
        [
            -1.7346489429473877
        ],
        [
            -1.7040340900421143
        ],
        [
            -1.6758679151535034
        ],
        [
            -1.6548800468444824
        ],
        [
            -1.5663573741912842
        ],
        [
            -1.4766550064086914
        ],
        [
            -1.4991796016693115
        ],
        [
            -1.491338849067688
        ],
        [
            -1.518602728843689
        ],
        [
            -1.631783366203308
        ],
        [
            -1.683637261390686
        ],
        [
            -1.674621343612671
        ],
        [
            -1.692857027053833
        ],
        [
            -1.6177858114242554
        ],
        [
            -1.601637840270996
        ],
        [
            -1.692040205001831
        ],
        [
            -1.6695716381072998
        ],
        [
            -1.6217117309570312
        ],
        [
            -1.593996286392212
        ],
        [
            -1.5396254062652588
        ]
    ],
    "test_actual": [
        -1.275495135471525,
        -1.3171576360791364,
        -1.295607954239026,
        -1.3645672922272731,
        -1.3602572965092687,
        -1.4608231708462442,
        -1.433526926965432,
        -1.2740582723989158,
        -1.3315238928059354,
        -1.2697479799309996,
        -1.104533060073693,
        -1.1562524151899225,
        -1.1260833354136268,
        -1.1390130258177282,
        -1.1663092696985407,
        -1.1979161027971807,
        -1.2108454964513706,
        -1.2007889386926642,
        -1.2065357974832773,
        -1.2496348644135868,
        -1.2395783066548804,
        -1.2165920584920724,
        -1.1892958146112602,
        -1.1936055135793529,
        -1.1979161027971807,
        -1.2223389172826862,
        -1.2697479799309996,
        -1.351637601823171,
        -1.350201035500474,
        -1.3616941595818781,
        -1.3329607558785448,
        -1.3990469612213967,
        -1.3961738285760021,
        -1.465132869814337,
        -1.4579494447010257,
        -1.4895556842998425,
        -1.5283453490119705,
        -1.5326553447299749,
        -1.4450194575470126,
        -1.4076666559074937,
        -1.3990469612213967,
        -1.4062297928348846,
        -1.55133189392469,
        -1.5312187784072773,
        -1.4967394061630654,
        -1.4996125388084607,
        -1.275495135471525,
        -1.2007889386926642,
        -1.1849861156431676,
        -1.1347030300997238,
        -1.1907323809339578,
        -1.1188996135504037,
        -1.0707753836148148,
        -1.0955664647407806,
        -1.0328587571430041,
        -1.0416087250403518,
        -0.9774430851262333,
        -0.9628599042139572,
        -1.003692395318453,
        -1.0197338052969827,
        -1.0153594148481317,
        -0.8636937992106254,
        -0.9964009532372716,
        -0.9686931172288862,
        -1.0532757445700311,
        -1.1232748942489887,
        -1.0678583319824833,
        -1.0007762339358566,
        -0.9059851128811977,
        -0.8797355059390662,
        -0.870986131541542,
        -0.9803595432587414,
        -1.0124423632158006,
        -1.0868164968434328,
        -1.0926500066082725,
        -1.1466080430586127,
        -1.148065975374955,
        -1.1655659111696504,
        -1.245773554562122,
        -1.183065550214434,
        -1.1349410235289334,
        -1.1349410235289334,
        -1.0445254799227712,
        -1.0984832196232002,
        -1.1816073211481801,
        -1.1261913523814975,
        -1.099941745439366,
        -1.064942170599887,
        -1.1218163684328235,
        -1.1407742365438613,
        -1.0897335484757642,
        -1.107233187520548,
        -1.1378583719111768,
        -1.0459837089890258,
        -1.0007762339358566,
        -0.9628599042139572,
        -0.9366097037720029,
        -0.8782772768728122,
        -0.8009863883627604,
        -0.8476526859820075,
        -0.8097363562601081,
        -0.8636937992106254,
        -0.8782772768728122,
        -0.8082784239437657,
        -0.7791117653693028,
        -0.6297429940486052,
        -0.6371377050990708,
        -0.5380511290720827,
        -0.6637573591811327,
        -0.647489529019951,
        -0.680025486092226,
        -0.7820694717395417,
        -0.8441830860140287,
        -0.9136914113389818,
        -0.9270018318798362,
        -0.9580584906421241,
        -0.9728473192432304,
        -0.9136914113389818,
        -0.9092550001585793,
        -0.9343965429303016,
        -0.9950311556447133,
        -0.9210861223894461,
        -0.9062969970384291,
        -0.8870711637570964,
        -0.9240435320097738,
        -0.9062969970384291,
        -0.9033392906681897,
        -0.9181284160192077,
        -0.9284802399400881,
        -0.932917244620314,
        -0.8900288701273352,
        -0.9950311556447133,
        -0.9817210318537706,
        -0.9639742001325137,
        -0.9565797858319606,
        -0.8308732589729984,
        -0.7820694717395417,
        -0.7939008907203209,
        -0.8678456272256764,
        -0.8515775003145825,
        -0.7332659812559968,
        -0.768759347948599,
        -0.7805904701794664,
        -0.7939008907203209,
        -0.8293942574129235,
        -0.8456623843240163,
        -0.8175631351820556,
        -0.9018602891081138,
        -0.8959451731175483,
        -0.8781977478964684,
        -0.9003815842979508,
        -0.9403116589208672,
        -0.9491850747814956,
        -0.9891154461543232,
        -0.9536217827118099,
        -0.8619299177352863,
        -0.8648879208554369,
        -0.7155188527848282,
        -0.8412253796437904,
        -0.8678456272256764,
        -0.8796770462064549,
        -0.8264362542927723,
        -0.7924218891602455,
        -0.8515775003145825,
        -0.8589725081149591,
        -0.9018602891081138,
        -0.9151704128990571,
        -0.9122124097789058,
        -0.9447483668511815,
        -0.9728473192432304,
        -0.9122124097789058,
        -0.9713689111829785,
        -0.9624949018225266,
        -0.9950311556447133,
        -1.0260878144070014,
        -1.074891601640458,
        -1.0408769397580193,
        -1.1340475095447065,
        -1.1192586809436003,
        -1.1673182193984315,
        -1.2394079722055464,
        -1.2469172287219394,
        -1.1673182193984315,
        -1.2724489976275897,
        -1.455677527376801,
        -1.4466661228072173,
        -1.4106210980287037,
        -1.4346510156310752,
        -1.4061158408687793,
        -1.3280186828485498,
        -1.2499212280784087,
        -1.3099958737093815,
        -1.3009847658897091,
        -1.2439138228652937,
        -1.3024866171929879,
        -1.3415353445780585,
        -1.3910970310860795,
        -1.3205088328323327,
        -1.3160035756724082,
        -1.2604341872013598,
        -1.340033196524868,
        -1.3910970310860795,
        -1.3700705193403544,
        -1.3385316419715014,
        -1.388093328479522,
        -1.2108725006933383,
        -1.2919736580700367,
        -1.3099958737093815,
        -1.2213854598162894,
        -1.168820367451622,
        -1.1643148135417858,
        -1.1913484337507148,
        -1.18233702918113,
        -1.212374351996617,
        -1.1958536909106385,
        -1.1838388804844093,
        -1.1868425830909661,
        -1.141786747242693,
        -1.10574172246418,
        -1.1462920044026175,
        -1.1673182193984315,
        -1.1553034089722016,
        -1.2138765000498073,
        -1.242411971562015,
        -1.201861392873666,
        -1.2303968643858734,
        -1.1793333265745725,
        -1.2739511456807802,
        -1.2093706493900596,
        -1.1971570165229688,
        -1.0796010227396544,
        -1.096394990494338,
        -1.116241921340926,
        -1.0719677247601564,
        -1.1315088140498335,
        -1.180363345518197,
        -1.2307443585325124,
        -1.1437224469169247,
        -1.2368511749660578,
        -1.2505915861290127,
        -1.2307443585325124,
        -1.2826521498426922,
        -1.291812522867966,
        -1.2658584788379204,
        -1.2826521498426922,
        -1.278072111705011,
        -1.2276910986906955,
        -1.2261643203948314,
        -1.1650964528092893,
        -1.1116618832032454,
        -1.097921768790202,
        -1.1467760035086534,
        -1.1956302382271045,
        -1.145249225212789,
        -1.1727297507887873,
        -1.2490648078331485,
        -1.220057503961286,
        -1.1742565290846516,
        -1.0994482503361547,
        -1.1131886614991098,
        -1.212424205981788,
        -1.2551716242666937,
        -1.2719652952714655,
        -1.2536451427207413,
        -1.2032638329565142,
        -1.1635696745134252,
        -1.1788368639722437,
        -1.1818898270641496,
        -1.1681497126511062,
        -1.1895237185434708,
        -1.2795988900008752,
        -1.331506681311055,
        -1.36204046672887,
        -1.331506681311055,
        -1.3116594537145552,
        -1.4337951888856384,
        -1.4093682199013686,
        -1.4719628657827748,
        -1.6734872145899482,
        -1.725395005900128,
        -1.8460039627753473,
        -1.7467687150425812,
        -1.8841716396724844,
        -1.8353171082041209,
        -1.8032565444904416,
        -1.7544020130220785,
        -1.8154698806076206,
        -1.8002032846486247,
        -1.8154698806076206,
        -1.7406618986090354,
        -1.7620359045014,
        -1.7024942217118995,
        -1.681120512569446,
        -1.6612735817228574,
        -1.548297626077224,
        -1.4536424164821387,
        -1.5269239169347713,
        -1.485702980195818,
        -1.5360839932101333,
        -1.687227625752903,
        -1.7009674434160342,
        -1.6734872145899482,
        -1.713938382057867,
        -1.5879167067926447,
        -1.6221447318616191,
        -1.7543898462756975,
        -1.6641520558666638,
        -1.6283681710104754,
        -1.6019191481276596,
        -1.5210162196919985,
        -1.5956957089788033
    ]
}